README.rst
setup.py
konfiger.egg-info/PKG-INFO
konfiger.egg-info/SOURCES.txt
konfiger.egg-info/dependency_links.txt
konfiger.egg-info/not-zip-safe
konfiger.egg-info/top_level.txt
src/__init__.py
src/konfiger.py
src/konfiger_stream.py
src/konfiger_util.py
test/test_konfiger.py
test/test_resolve.py
test/test_stream.py
test/test_util.py