Metadata-Version: 1.1
Name: konfiger
Version: 1.2.4
Summary: Light weight package to manage key value based configuration and data files for Python
Home-page: https://konfiger.github.io/konfiger-python
Author: Adewale Azeez
Author-email: azeezadewale98@gmail.com
License: MIT
Keywords: key-value,database,python,package,thecarisma,quick,simple,dictionary
Platform: any
Classifier: Development Status :: 5 - Production/Stable
Classifier: Natural Language :: English
Classifier: Topic :: Database
Classifier: Topic :: Database :: Database Engines/Servers
Classifier: Topic :: Database :: Front-Ends
Classifier: Programming Language :: Python
Classifier: Programming Language :: Python :: 2.7
Classifier: Programming Language :: Python :: 3
Classifier: Programming Language :: Python :: 3.4
Classifier: Programming Language :: Python :: 3.5
Classifier: Programming Language :: Python :: 3.6
Classifier: Programming Language :: Python :: 3.7
